pyremo/__init__.py
pyremo/cal.py
pyremo/cli.py
pyremo/codes.py
pyremo/conventions.py
pyremo/data.py
pyremo/domain.py
pyremo/remo_ds.py
pyremo/tutorial.py
pyremo/utils.py
pyremo/analysis/__init__.py
pyremo/analysis/_parser.py
pyremo/analysis/analysis.py
pyremo/analysis/obs.py
pyremo/analysis/plot.py
pyremo/analysis/resources.py
pyremo/archive/__init__.py
pyremo/archive/archive.py
pyremo/core/__init__.py
pyremo/core/cli.py
pyremo/core/data_handler.py
pyremo/core/exp.py
pyremo/core/file_conventions.py
pyremo/physics/__init__.py
pyremo/physics/constants.py
pyremo/physics/core.py
pyremo/physics/physics.py
pyremo/physics/units.py
pyremo/preproc/__init__.py
pyremo/preproc/cf.py
pyremo/preproc/constants.py
pyremo/preproc/core.py
pyremo/preproc/ecmwf_128.csv
pyremo/preproc/era5-params.yaml
pyremo/preproc/era5.py
pyremo/preproc/grid.txt
pyremo/preproc/physics.py
pyremo/preproc/preprocessor.py
pyremo/preproc/remapping.py
pyremo/preproc/utils.py
pyremo/preproc/xpyintorg.py
pyremo/prsint/__init__.py
pyremo/prsint/_defaults.py
pyremo/prsint/cli.py
pyremo/prsint/core.py
pyremo/tables/__init__.py
pyremo/tables/_resources.py
pyremo-0.8.3.dist-info/licenses/LICENSE
pyremo-0.8.3.dist-info/METADATA
pyremo-0.8.3.dist-info/WHEEL
pyremo-0.8.3.dist-info/entry_points.txt
pyremo-0.8.3.dist-info/top_level.txt
pyremo-0.8.3.dist-info/RECORD
