Metadata-Version: 2.4
Name: pyremo
Version: 0.8.3
Summary: Data analytics, processing and plotting for regional climate model REMO.
License: MIT License
Project-URL: homepage, https://pyremo.readthedocs.io
Project-URL: documentation, https://pyremo.readthedocs.io
Project-URL: repository, https://github.com/remo-rcm/pyremo.git
Project-URL: changelog, https://pyremo.readthedocs.io/en/latest/whats-new.html
Keywords: remo,cordex
Classifier: Development Status :: 5 - Production/Stable
Classifier: License :: OSI Approved :: MIT License
Classifier: Natural Language :: English
Classifier: Operating System :: OS Independent
Classifier: Programming Language :: Python
Classifier: Programming Language :: Python :: 3.9
Classifier: Programming Language :: Python :: 3.10
Classifier: Programming Language :: Python :: 3.11
Classifier: Programming Language :: Python :: 3.12
Requires-Python: >=3.9
License-File: LICENSE
Requires-Dist: numpy
Requires-Dist: pooch>=1.0
Requires-Dist: setuptools>=40.4
Requires-Dist: xarray>=0.15
Requires-Dist: py-cordex>=0.3.0
Dynamic: license-file
